configarg/__init__.py
configarg/config.py
configarg-0.1.1.dist-info/LICENSE
configarg-0.1.1.dist-info/WHEEL
configarg-0.1.1.dist-info/METADATA
configarg-0.1.1.dist-info/RECORD
