Metadata-Version: 2.1
Name: configarg
Version: 0.1.1
Summary: Configuration file with argparse
License: MIT
Author: NEWROPE Co. Ltd.
Author-email: dev@newrope.biz
Requires-Python: >=3.8,<4.0
Classifier: License :: OSI Approved :: MIT License
Classifier: Programming Language :: Python :: 3
Classifier: Programming Language :: Python :: 3.8
Classifier: Programming Language :: Python :: 3.9
